races_report/__about__.py
races_report/__init__.py
races_report/custom_exceptions.py
races_report/main.py
races_report/races_report.py
races_report-0.0.5.dist-info/METADATA
races_report-0.0.5.dist-info/WHEEL
races_report-0.0.5.dist-info/licenses/LICENSE.txt
races_report-0.0.5.dist-info/RECORD
