Metadata-Version: 2.1
Name: races_report
Version: 0.0.5
Summary: A small package for builds a races report depending on the command line arguments
Author-email: Oleh Holub <golub.zp@google.com>
License: MIT License
License-File: LICENSE.txt
Classifier: License :: OSI Approved :: MIT License
Classifier: Operating System :: OS Independent
Classifier: Programming Language :: Python :: 3
Requires-Python: >=3.8
Requires-Dist: prettytable
